{
  "order": {
    "created_at": "2012-10-24T11:04:32-04:00",
    "id": 1234567,
    "refunded_at": null,
    "state": "completed",
    "balance": {
      "amount": 0,
      "currency_code": "USD",
      "currency_symbol": "$",
      "formatted_amount": "0.00"
      },
    "credit": {
      "amount": 1,
      "currency_code": "USD",
      "currency_symbol": "$",
      "formatted_amount": "0.01"
    },
    "earn": {
      "amount": 0,
      "currency_code": "USD",
      "currency_symbol": "$",
      "formatted_amount": "0.00"
    },
    "unfunded_credit": {
      "amount": 1,
      "currency_code": "USD",
      "currency_symbol": "$",
      "formatted_amount": "0.01"
    },
    "spend": {
      "amount": 1,
      "currency_code": "USD",
      "currency_symbol": "$",
      "formatted_amount": "0.01"
    },
    "tip": {
      "amount": 0,
      "currency_code": "USD",
      "currency_symbol": "$",
      "formatted_amount": "0.00"
    },
    "total": {
      "amount": 1,
      "currency_code": "USD",
      "currency_symbol": "$",
      "formatted_amount": "0.01"
    },
    "location": {
      "id": 4418,
      "extended_address": "",
      "lat": "40.907783",
      "lng": "-79.924102",
      "locality": "Boston",
      "phone": "",
      "postal_code": "02114",
      "region": "MA",
      "street_address": "1234 Test Street"
    },
    "loyalty": {
      "orders_count": 2,
      "progress_percent": 0,
      "onboarding_eligible": false,
      "potential_credit": {
        "amount": 19999,
        "currency_code": "USD",
        "currency_symbol": "$",
        "formatted_amount": "199.99"
      },
      "savings": {
        "amount": 1,
        "currency_code": "USD",
        "currency_symbol": "$",
        "formatted_amount": "0.01"
      },
      "spend_remaining": {
        "amount": 9999,
        "currency_code": "USD",
        "currency_symbol": "$",
        "formatted_amount": "99.99"
      }
    },
    "merchant": {
      "id": 1234,
      "name": "API Example Merchant",
      "message_for_twitter": null,
      "public_url": "https://www.thelevelup.com/merchants/1234",
      "image_url_280x128_1x": "https://s3.amazonaws.com/levelup-production/merchants/1234/images/280x128_1x/fposlogo.png?1346946087",
      "image_url_280x128_1_5x": "https://s3.amazonaws.com/levelup-production/merchants/1234/images/280x128_1_5x/fposlogo.png?1346946087",
      "image_url_280x128_2x": "https://s3.amazonaws.com/levelup-production/merchants/1234/images/280x128_2x/fposlogo.png?1346946087",
      "image_url_290x335_1x": "https://s3.amazonaws.com/levelup-production/merchants/1234/images/290x335_1x/fposlogo.png?1346946087",
      "image_url_320x212_1x": "https://s3.amazonaws.com/levelup-production/merchants/1234/images/320x212_1x/fposlogo.png?1346946087",
      "image_url_320x212_1_5x": "https://s3.amazonaws.com/levelup-production/merchants/1234/images/320x212_1_5x/fposlogo.png?1346946087",
      "image_url_320x212_2x": "https://s3.amazonaws.com/levelup-production/merchants/1234/images/320x212_2x/fposlogo.png?1346946087",
      "image_url_400x235_1x": "https://s3.amazonaws.com/levelup-production/merchants/1234/images/400x235_1x/fposlogo.png?1346946087"
    },
    "user": {
      "able_to_refer": true,
      "first_name": "Example",
      "last_initial": "M"
    }
  }
}